starmatrix/__init__.py
starmatrix/abundances.py
starmatrix/cli.py
starmatrix/constants.py
starmatrix/dtds.py
starmatrix/elements.py
starmatrix/functions.py
starmatrix/imfs.py
starmatrix/matrix.py
starmatrix/model.py
starmatrix/settings.py
starmatrix/supernovae.py
starmatrix/sample_input/expelled_elements
starmatrix/sample_input/params.yml
starmatrix/tests/__init__.py
starmatrix/tests/test_abundances.py
starmatrix/tests/test_cli.py
starmatrix/tests/test_dtds.py
starmatrix/tests/test_elements.py
starmatrix/tests/test_functions.py
starmatrix/tests/test_imfs.py
starmatrix/tests/test_matrix.py
starmatrix/tests/test_model.py
starmatrix/tests/test_settings.py
starmatrix/tests/test_supernovae.py
starmatrix/tests/dtds/__init__.py
starmatrix/tests/dtds/test_strolger.py
starmatrix-1.7.4.dist-info/LICENSE
starmatrix-1.7.4.dist-info/METADATA
starmatrix-1.7.4.dist-info/WHEEL
starmatrix-1.7.4.dist-info/entry_points.txt
starmatrix-1.7.4.dist-info/top_level.txt
starmatrix-1.7.4.dist-info/RECORD
