Metadata-Version: 2.1
Name: starmatrix
Version: 1.7.4
Summary: Modelling nucleosynthesis of galactic chemical elements using Q-Matrices
Home-page: https://github.com/xuanxu/starmatrix
Download-URL: https://github.com/xuanxu/starmatrix
Author: Juanjo Bazán
Author-email: hello@juanjobazan.com
License: MIT
Keywords: galaxies,models,astrophysics
Classifier: Development Status :: 5 - Production/Stable
Classifier: Intended Audience :: Science/Research
Classifier: Intended Audience :: Education
Classifier: License :: OSI Approved :: MIT License
Classifier: Operating System :: OS Independent
Classifier: Programming Language :: Python
Classifier: Programming Language :: Python :: 3
Classifier: Programming Language :: Python :: 3.7
Classifier: Programming Language :: Python :: 3.8
Classifier: Programming Language :: Python :: 3.9
Classifier: Programming Language :: Python :: 3.10
Classifier: Programming Language :: Python :: 3.11
Classifier: Programming Language :: Python :: Implementation :: CPython
Classifier: Topic :: Scientific/Engineering
Classifier: Topic :: Scientific/Engineering :: Astronomy
Classifier: Topic :: Scientific/Engineering :: Physics
Requires-Python: >=3.7
License-File: LICENSE
Requires-Dist: pyyaml (>=5.4.1)
Requires-Dist: numpy (>=1.20)
Requires-Dist: scipy (>=1.7)
Provides-Extra: dev
Requires-Dist: pytest (>=6.2) ; extra == 'dev'
Requires-Dist: pytest-mock (>=3.6) ; extra == 'dev'
Requires-Dist: pytest-cov (>=3.0) ; extra == 'dev'
